pip_build_standalone/__init__.py
pip_build_standalone/build.py
pip_build_standalone/cli.py
pip_build_standalone/cli_utils.py
pip_build_standalone/py.typed
pip_build_standalone/search_replace_files.py
pip_build_standalone/shebangs.py
pip_build_standalone-0.1.3.dist-info/METADATA
pip_build_standalone-0.1.3.dist-info/WHEEL
pip_build_standalone-0.1.3.dist-info/entry_points.txt
pip_build_standalone-0.1.3.dist-info/licenses/LICENSE
pip_build_standalone-0.1.3.dist-info/RECORD
